MANIFEST.in
README.md
setup.py
src/gaussdca/__init__.py
src/gaussdca/_gdca.cpp
src/gaussdca/_gdca.py
src/gaussdca/_load_data.cpp
src/gaussdca/_load_data.py
src/gaussdca/gaussdca.py
src/pyGaussDCA.egg-info/PKG-INFO
src/pyGaussDCA.egg-info/SOURCES.txt
src/pyGaussDCA.egg-info/dependency_links.txt
src/pyGaussDCA.egg-info/not-zip-safe
src/pyGaussDCA.egg-info/requires.txt
src/pyGaussDCA.egg-info/top_level.txt
tests/__init__.py
tests/run_tests.sh
tests/test_gaussdca.py
tests/__pycache__/__init__.cpython-36.pyc
tests/__pycache__/test_gaussdca.cpython-36-PYTEST.pyc
tests/data/large.a3m
tests/data/small.a3m
tests/data/small.aln