Metadata-Version: 1.1
Name: pyGaussDCA
Version: 1.0
Summary: Fast implementation of GaussDCA
Home-page: https://github.com/ElofssonLab/pyGaussDCA/
Author: David Menéndez Hurtado
Author-email: davidmenhur@gmail.com
License: GPLv3
Platform: UNKNOWN
Classifier: Programming Language :: Python
Classifier: Topic :: Scientific/Engineering :: Bio-Informatics
Classifier: Intended Audience :: Science/Research
